<Ifmgr>
    <Interfaces>
        <Interface>
            <IfIndex>1</IfIndex>
            <LinkType>2</LinkType>
        </Interface>
        <Interface>
            <IfIndex>2</IfIndex>
            <LinkType>2</LinkType>
        </Interface>
        <Interface>
            <IfIndex>3</IfIndex>
            <LinkType>2</LinkType>
        </Interface>
        <Interface>
            <IfIndex>4</IfIndex>
            <LinkType>2</LinkType>
        </Interface>
        <Interface>
            <IfIndex>5</IfIndex>
            <LinkType>2</LinkType>
        </Interface>
        <Interface>
            <IfIndex>6</IfIndex>
            <LinkType>2</LinkType>
        </Interface>
        <Interface>
            <IfIndex>7</IfIndex>
            <LinkType>2</LinkType>
        </Interface>
        <Interface>
            <IfIndex>8</IfIndex>
            <LinkType>2</LinkType>
        </Interface>
        <Interface>
            <IfIndex>9</IfIndex>
            <LinkType>2</LinkType>
        </Interface>
        <Interface>
            <IfIndex>10</IfIndex>
            <LinkType>2</LinkType>
        </Interface>
        <Interface>
            <IfIndex>11</IfIndex>
            <LinkType>2</LinkType>
        </Interface>
        <Interface>
            <IfIndex>12</IfIndex>
            <LinkType>2</LinkType>
        </Interface>
        <Interface>
            <IfIndex>13</IfIndex>
            <LinkType>2</LinkType>
        </Interface>
        <Interface>
            <IfIndex>14</IfIndex>
            <LinkType>2</LinkType>
        </Interface>
        <Interface>
            <IfIndex>15</IfIndex>
            <LinkType>1</LinkType>
            <PVID>151</PVID>
        </Interface>
        <Interface>
            <IfIndex>16</IfIndex>
            <LinkType>1</LinkType>
            <PVID>151</PVID>
        </Interface>
        <Interface>
            <IfIndex>17</IfIndex>
            <LinkType>1</LinkType>
            <PVID>151</PVID>
        </Interface>
        <Interface>
            <IfIndex>18</IfIndex>
            <LinkType>1</LinkType>
            <PVID>151</PVID>
        </Interface>
        <Interface>
            <IfIndex>19</IfIndex>
            <LinkType>1</LinkType>
            <PVID>151</PVID>
        </Interface>
        <Interface>
            <IfIndex>20</IfIndex>
            <LinkType>1</LinkType>
            <PVID>151</PVID>
        </Interface>
        <Interface>
            <IfIndex>21</IfIndex>
            <LinkType>1</LinkType>
            <PVID>151</PVID>
        </Interface>
        <Interface>
            <IfIndex>22</IfIndex>
            <LinkType>1</LinkType>
            <PVID>151</PVID>
        </Interface>
        <Interface>
            <IfIndex>23</IfIndex>
            <LinkType>1</LinkType>
            <PVID>151</PVID>
        </Interface>
        <Interface>
            <IfIndex>24</IfIndex>
            <LinkType>1</LinkType>
            <PVID>151</PVID>
        </Interface>
        <Interface>
            <IfIndex>25</IfIndex>
            <LinkType>1</LinkType>
            <PVID>151</PVID>
        </Interface>
        <Interface>
            <IfIndex>29</IfIndex>
            <LinkType>2</LinkType>
        </Interface>
        <Interface>
            <IfIndex>30</IfIndex>
            <LinkType>2</LinkType>
        </Interface>
        <Interface>
            <IfIndex>31</IfIndex>
            <LinkType>2</LinkType>
        </Interface>
        <Interface>
            <IfIndex>32</IfIndex>
            <LinkType>2</LinkType>
        </Interface>
        <Interface>
            <IfIndex>33</IfIndex>
            <LinkType>2</LinkType>
        </Interface>
        <Interface>
            <IfIndex>34</IfIndex>
            <LinkType>2</LinkType>
        </Interface>
        <Interface>
            <IfIndex>35</IfIndex>
            <LinkType>2</LinkType>
        </Interface>
        <Interface>
            <IfIndex>36</IfIndex>
            <LinkType>2</LinkType>
        </Interface>
        <Interface>
            <IfIndex>37</IfIndex>
            <LinkType>2</LinkType>
        </Interface>
        <Interface>
            <IfIndex>38</IfIndex>
            <LinkType>2</LinkType>
        </Interface>
        <Interface>
            <IfIndex>39</IfIndex>
            <LinkType>2</LinkType>
        </Interface>
        <Interface>
            <IfIndex>40</IfIndex>
            <LinkType>2</LinkType>
        </Interface>
        <Interface>
            <IfIndex>49</IfIndex>
            <LinkType>2</LinkType>
        </Interface>
        <Interface>
            <IfIndex>54</IfIndex>
            <LinkType>2</LinkType>
        </Interface>
        <Interface>
            <IfIndex>162</IfIndex>
            <LinkType>2</LinkType>
        </Interface>
        <Interface>
            <IfIndex>163</IfIndex>
            <LinkType>2</LinkType>
        </Interface>
        <Interface>
            <IfIndex>164</IfIndex>
            <LinkType>2</LinkType>
        </Interface>
        <Interface>
            <IfIndex>165</IfIndex>
            <LinkType>2</LinkType>
        </Interface>
        <Interface>
            <IfIndex>166</IfIndex>
            <LinkType>2</LinkType>
        </Interface>
        <Interface>
            <IfIndex>167</IfIndex>
            <LinkType>2</LinkType>
        </Interface>
        <Interface>
            <IfIndex>168</IfIndex>
            <LinkType>2</LinkType>
        </Interface>
        <Interface>
            <IfIndex>169</IfIndex>
            <LinkType>2</LinkType>
        </Interface>
        <Interface>
            <IfIndex>170</IfIndex>
            <LinkType>2</LinkType>
        </Interface>
        <Interface>
            <IfIndex>171</IfIndex>
            <LinkType>2</LinkType>
        </Interface>
        <Interface>
            <IfIndex>172</IfIndex>
            <LinkType>2</LinkType>
        </Interface>
        <Interface>
            <IfIndex>173</IfIndex>
            <LinkType>2</LinkType>
        </Interface>
        <Interface>
            <IfIndex>174</IfIndex>
            <LinkType>2</LinkType>
        </Interface>
        <Interface>
            <IfIndex>175</IfIndex>
            <LinkType>2</LinkType>
        </Interface>
        <Interface>
            <IfIndex>176</IfIndex>
            <LinkType>1</LinkType>
            <PVID>151</PVID>
        </Interface>
        <Interface>
            <IfIndex>177</IfIndex>
            <LinkType>1</LinkType>
            <PVID>151</PVID>
        </Interface>
        <Interface>
            <IfIndex>178</IfIndex>
            <LinkType>1</LinkType>
            <PVID>151</PVID>
        </Interface>
        <Interface>
            <IfIndex>179</IfIndex>
            <LinkType>1</LinkType>
            <PVID>151</PVID>
        </Interface>
        <Interface>
            <IfIndex>180</IfIndex>
            <LinkType>1</LinkType>
            <PVID>151</PVID>
        </Interface>
        <Interface>
            <IfIndex>181</IfIndex>
            <LinkType>1</LinkType>
            <PVID>151</PVID>
        </Interface>
        <Interface>
            <IfIndex>182</IfIndex>
            <LinkType>1</LinkType>
            <PVID>151</PVID>
        </Interface>
        <Interface>
            <IfIndex>183</IfIndex>
            <LinkType>1</LinkType>
            <PVID>151</PVID>
        </Interface>
        <Interface>
            <IfIndex>184</IfIndex>
            <LinkType>1</LinkType>
            <PVID>151</PVID>
        </Interface>
        <Interface>
            <IfIndex>185</IfIndex>
            <LinkType>1</LinkType>
            <PVID>151</PVID>
        </Interface>
        <Interface>
            <IfIndex>186</IfIndex>
            <LinkType>1</LinkType>
            <PVID>151</PVID>
        </Interface>
        <Interface>
            <IfIndex>187</IfIndex>
            <LinkType>1</LinkType>
            <PVID>151</PVID>
        </Interface>
        <Interface>
            <IfIndex>190</IfIndex>
            <LinkType>2</LinkType>
        </Interface>
        <Interface>
            <IfIndex>191</IfIndex>
            <LinkType>2</LinkType>
        </Interface>
        <Interface>
            <IfIndex>192</IfIndex>
            <LinkType>2</LinkType>
        </Interface>
        <Interface>
            <IfIndex>193</IfIndex>
            <LinkType>2</LinkType>
        </Interface>
        <Interface>
            <IfIndex>194</IfIndex>
            <LinkType>2</LinkType>
        </Interface>
        <Interface>
            <IfIndex>195</IfIndex>
            <LinkType>2</LinkType>
        </Interface>
        <Interface>
            <IfIndex>196</IfIndex>
            <LinkType>2</LinkType>
        </Interface>
        <Interface>
            <IfIndex>197</IfIndex>
            <LinkType>2</LinkType>
        </Interface>
        <Interface>
            <IfIndex>198</IfIndex>
            <LinkType>2</LinkType>
        </Interface>
        <Interface>
            <IfIndex>199</IfIndex>
            <LinkType>2</LinkType>
        </Interface>
        <Interface>
            <IfIndex>200</IfIndex>
            <LinkType>2</LinkType>
        </Interface>
        <Interface>
            <IfIndex>201</IfIndex>
            <LinkType>2</LinkType>
        </Interface>
        <Interface>
            <IfIndex>210</IfIndex>
            <LinkType>2</LinkType>
        </Interface>
        <Interface>
            <IfIndex>215</IfIndex>
            <LinkType>2</LinkType>
        </Interface>
    </Interfaces>
</Ifmgr>
